blake3-1.0.8.dist-info/METADATA
blake3-1.0.8.dist-info/WHEEL
blake3-1.0.8.dist-info/licenses/LICENSE
blake3/__init__.py
blake3/__init__.pyi
blake3/blake3.cp312-win_amd64.pyd
blake3/py.typed
blake3-1.0.8.dist-info/RECORD
