Metadata-Version: 2.4
Name: blake3
Version: 1.0.8
Classifier: Development Status :: 5 - Production/Stable
Classifier: Programming Language :: Python
Classifier: Programming Language :: Python :: 3 :: Only
Classifier: Programming Language :: Python :: Free Threading
Classifier: Programming Language :: Rust
Classifier: Topic :: Security
Classifier: Topic :: Security :: Cryptography
Classifier: Topic :: Utilities
Requires-Dist: typing-extensions>=4.6.0 ; python_full_version < '3.12'
License-File: LICENSE
Summary: Python bindings for the Rust blake3 crate
Home-Page: https://github.com/oconnor663/blake3-py
Author: Jack O'Connor <oconnor663@gmail.com>
Author-email: Jack O'Connor <oconnor663@gmail.com>
License: CC0-1.0 OR Apache-2.0
Requires-Python: >=3.8
Project-URL: Source Code, https://github.com/oconnor663/blake3-py
